app/__init__.py
app/cli.py
app/cli_entry.py
app/context_manager.py
app/context_store.py
app/main.py
app/mcp/__init__.py
app/mcp/cli.py
app/mcp/server.py
app/memory/__init__.py
app/memory/core.py
app/memory/manager.py
app/memory/store.py
app/models.py
app/retrieval.py
app/storage/__init__.py
app/storage/sqlite_storage.py
app/storage/storage_adapter.py
app/vector_store/__init__.py
app/vector_store/usearch_vector_store.py
app/vector_store/vector_store.py
app/window_optimizer.py
memorg-0.1.2.dist-info/LICENSE
memorg-0.1.2.dist-info/METADATA
memorg-0.1.2.dist-info/WHEEL
memorg-0.1.2.dist-info/entry_points.txt
memorg-0.1.2.dist-info/RECORD
