Metadata-Version: 2.3
Name: memorg
Version: 0.1.2
Summary: A hierarchical context management system for Large Language Models that acts as an external memory layer, helping LLMs maintain context over extended interactions while managing token usage efficiently.
License: MIT
Keywords: llm,context-management,memory,ai,nlp,openai
Author: Dipankar Sarkar
Author-email: me@dipankar.name
Requires-Python: >=3.11,<4.0
Classifier: Development Status :: 3 - Alpha
Classifier: Intended Audience :: Developers
Classifier: License :: OSI Approved :: MIT License
Classifier: Programming Language :: Python :: 3
Classifier: Programming Language :: Python :: 3.11
Classifier: Programming Language :: Python :: 3.12
Classifier: Programming Language :: Python :: 3.13
Classifier: Topic :: Scientific/Engineering :: Artificial Intelligence
Classifier: Topic :: Software Development :: Libraries :: Python Modules
Requires-Dist: aiosqlite (>=0.21.0,<0.22.0)
Requires-Dist: fastmcp (>=0.1.0,<0.2.0)
Requires-Dist: numpy (>=2.2.6,<3.0.0)
Requires-Dist: openai (>=1.79.0,<2.0.0)
Requires-Dist: python-dotenv (>=1.1.0,<2.0.0)
Requires-Dist: rich (>=14.0.0,<15.0.0)
Requires-Dist: tiktoken (>=0.9.0,<0.10.0)
Requires-Dist: usearch (>=2.17.7,<3.0.0)
Project-URL: Documentation, https://github.com/skelf-research/memorg
Project-URL: Homepage, https://github.com/skelf-research/memorg
Project-URL: Repository, https://github.com/skelf-research/memorg
